mcdreforged/__init__.py
mcdreforged/__main__.py
mcdreforged/mcdr_boostrap.py
mcdreforged/mcdr_config.py
mcdreforged/mcdr_entrypoint.py
mcdreforged/mcdr_server.py
mcdreforged/mcdr_server_args.py
mcdreforged/mcdr_state.py
mcdreforged/py.typed
mcdreforged/api/__init__.py
mcdreforged/api/all/__init__.py
mcdreforged/api/command/__init__.py
mcdreforged/api/decorator/__init__.py
mcdreforged/api/decorator/event_listener.py
mcdreforged/api/decorator/new_thread.py
mcdreforged/api/decorator/spam_proof.py
mcdreforged/api/event/__init__.py
mcdreforged/api/exception/__init__.py
mcdreforged/api/rcon/__init__.py
mcdreforged/api/rtext/__init__.py
mcdreforged/api/types/__init__.py
mcdreforged/api/utils/__init__.py
mcdreforged/api/utils/serializer.py
mcdreforged/cli/__init__.py
mcdreforged/cli/cli_entry.py
mcdreforged/cli/cmd_gendefault.py
mcdreforged/cli/cmd_init.py
mcdreforged/cli/cmd_pack.py
mcdreforged/cli/cmd_pim.py
mcdreforged/cli/cmd_reformat_config.py
mcdreforged/cli/cmd_run.py
mcdreforged/cli/cmd_version.py
mcdreforged/command/__init__.py
mcdreforged/command/command_manager.py
mcdreforged/command/command_source.py
mcdreforged/command/builder/__init__.py
mcdreforged/command/builder/callback.py
mcdreforged/command/builder/command_builder_utils.py
mcdreforged/command/builder/common.py
mcdreforged/command/builder/exception.py
mcdreforged/command/builder/tools.py
mcdreforged/command/builder/nodes/__init__.py
mcdreforged/command/builder/nodes/arguments.py
mcdreforged/command/builder/nodes/basic.py
mcdreforged/command/builder/nodes/special.py
mcdreforged/constants/__init__.py
mcdreforged/constants/core_constant.py
mcdreforged/constants/deprecations.py
mcdreforged/constants/environment_variables.py
mcdreforged/constants/plugin_constant.py
mcdreforged/executor/__init__.py
mcdreforged/executor/background_thread_executor.py
mcdreforged/executor/console_handler.py
mcdreforged/executor/task_executor_async.py
mcdreforged/executor/task_executor_common.py
mcdreforged-2.15.5.dist-info/licenses/LICENSE
mcdreforged-2.15.5.dist-info/METADATA
mcdreforged-2.15.5.dist-info/WHEEL
mcdreforged-2.15.5.dist-info/entry_points.txt
mcdreforged-2.15.5.dist-info/top_level.txt
mcdreforged-2.15.5.dist-info/RECORD
