Metadata-Version: 2.4
Name: mcdreforged
Version: 2.15.5
Summary: A rewritten version of MCDaemon, a python tool to control your Minecraft server
Author: Fallen_Breath
License-Expression: LGPL-3.0-only
Project-URL: Documentation, https://docs.mcdreforged.com
Project-URL: Homepage, https://github.com/MCDReforged/MCDReforged
Classifier: Operating System :: OS Independent
Classifier: Programming Language :: Python
Classifier: Programming Language :: Python :: 3
Classifier: Programming Language :: Python :: 3.9
Classifier: Programming Language :: Python :: 3.10
Classifier: Programming Language :: Python :: 3.11
Classifier: Programming Language :: Python :: 3.12
Classifier: Programming Language :: Python :: 3.13
Requires-Python: >=3.9
License-File: LICENSE
Requires-Dist: colorama>=0.4.4
Requires-Dist: colorlog>=6.4
Requires-Dist: packaging>=23.0
Requires-Dist: parse>=1.18.0
Requires-Dist: pathspec
Requires-Dist: prompt-toolkit~=3.0
Requires-Dist: psutil>=5.8.0
Requires-Dist: requests>=2.26
Requires-Dist: resolvelib
Requires-Dist: ruamel.yaml~=0.17
Requires-Dist: typing-extensions>=4.6.0
Requires-Dist: wcwidth
Provides-Extra: dev
Requires-Dist: build; extra == "dev"
Requires-Dist: setuptools>=77.0.3; extra == "dev"
Requires-Dist: pydantic; extra == "dev"
Requires-Dist: mypy>=1.17; extra == "dev"
Requires-Dist: types-colorama; extra == "dev"
Requires-Dist: types-psutil; extra == "dev"
Requires-Dist: types-requests; extra == "dev"
Dynamic: license-file
